<?xml version='1.0' encoding='utf-8'?><m:layout id='0377a6dd-9b11-4c30-b76d-aae6db7192a2' xmlns='http://www.w3.org/1999/xhtml' xmlns:m='http://schemas.mendix.com/forms/1.0'><m:arguments><m:argument><div data-mendix-id='4.Atlas_Core.Phone_TopBar.scrollContainer1' data-mendix-type='mxui.widget.VerticalScrollContainer' data-mendix-props='"fixed":true,"config":[{"position":"top"},{"position":"middle"}]' class='mx-scrollcontainer mx-scrollcontainer-vertical mx-scrollcontainer-fixed'><div class='mx-scrollcontainer-top region-topbar'><div class='mx-scrollcontainer-wrapper'><div class='mx-header mx-name-header1'><div class='mx-header-center'><div data-mendix-id='4.2' data-mendix-type='mxui.widget.ReactWidgetWrapper' data-mendix-props='"widgetTree":[{"$widgetId":"4.2","widget":"Title","props":{"class":"","caption":{"$type":"ExpressionProperty","expression":{"expr":{"type":"variable","variable":"pageTitle"},"args":{}}}}}],"listenTargets":[]'></div></div><div class='mx-header-left'><div data-mx-placeholder='a4a652e6-8424-4639-b71b-150fb10bcd84' class='mx-placeholder'></div></div><div class='mx-header-right'><div data-mx-placeholder='f86fbbdb-7eb6-4916-8b85-bb95ce9803ab' class='mx-placeholder'></div></div></div></div></div><div class='mx-scrollcontainer-middle region-content'><div class='mx-scrollcontainer-wrapper'><div data-mx-placeholder='f399df31-1d06-4d53-8c55-d7f18bd40a71' class='mx-placeholder'></div></div></div></div></m:argument></m:arguments></m:layout>